linuk/__init__.py
linuk/basic.py
linuk-1.0.1.dist-info/LICENSE
linuk-1.0.1.dist-info/METADATA
linuk-1.0.1.dist-info/WHEEL
linuk-1.0.1.dist-info/top_level.txt
linuk-1.0.1.dist-info/RECORD
